pymylib/__init__.py
pymylib/main.py
pymylib/pymylib/__init__.py
pymylib/pymylib/auxiliars.py
pymylib/pymylib/base.py
pymylib/pymylib/collections.py
pymylib/pymylib/github.py
pymylib-1.dist-info/LICENSE
pymylib-1.dist-info/METADATA
pymylib-1.dist-info/WHEEL
pymylib-1.dist-info/top_level.txt
pymylib-1.dist-info/RECORD
